skill_manager/__init__.py
skill_manager/agents.py
skill_manager/cli.py
skill_manager/deployment.py
skill_manager/github.py
skill_manager/metadata.py
skill_manager/removal.py
skill_manager/validation.py
agent_skill_manager-0.1.3.dist-info/METADATA
agent_skill_manager-0.1.3.dist-info/WHEEL
agent_skill_manager-0.1.3.dist-info/entry_points.txt
agent_skill_manager-0.1.3.dist-info/RECORD
