Metadata-Version: 2.4
Name: agent-skill-manager
Version: 0.1.3
Summary: CLI tool for managing AI agent skills across multiple platforms
Project-URL: Homepage, https://github.com/ackness/skill-manager
Project-URL: Repository, https://github.com/ackness/skill-manager
Project-URL: Issues, https://github.com/ackness/skill-manager/issues
Project-URL: Documentation, https://github.com/ackness/skill-manager#readme
Author-email: ackness <ackness8@gmail.com>
License: MIT
Keywords: agents,ai,claude,cli,cursor,skills,windsurf
Classifier: Development Status :: 4 - Beta
Classifier: Intended Audience :: Developers
Classifier: License :: OSI Approved :: MIT License
Classifier: Programming Language :: Python :: 3
Classifier: Programming Language :: Python :: 3.13
Classifier: Topic :: Software Development :: Libraries
Classifier: Topic :: Utilities
Requires-Python: >=3.13
Requires-Dist: httpx>=0.28.1
Requires-Dist: inquirerpy>=0.3.4
Requires-Dist: loguru>=0.7.3
Requires-Dist: rich>=14.2.0
